{"file":"index-BpFK4D3P.js","mappings":";;;;;;;;;;;;;;;;;;;;;;;;;;;;AAAA,SAAA,eAAA,MAAA,OAAA,SACkB;AADlB,QAAA,OAAAA,eAAAC,WAAA,EAAA,OAAA,gBAAA,MAAA,CAAA,CAAA,gIAAA;AAAAC,gBAAA,KAAA,QAAA,WAAA,CAAA,GAAA,MAAA,OAAA,OAAA;;;;;;;;;;","names":["_ssrRenderAttrs","_mergeProps","_ssrRenderSlot"],"sources":["../../../../src/pages/challenges/index/components/border3Box/index.vue"],"sourcesContent":["<template>\r\n        <div class=\"border3Box\">\r\n                <p class=\"line1\"></p>\r\n                <p class=\"line2\"></p>\r\n                <div class=\"inner\">\r\n                        <slot></slot>\r\n                </div>\r\n                <p class=\"line3\"></p>\r\n                <p class=\"line4\"></p>\r\n        </div>\r\n</template>\r\n<script setup>\r\n</script>\r\n<style scoped lang=\"scss\">\r\n.border3Box {\r\n        width: auto;\r\n        height: 100%;\r\n        position: relative;\r\n        $radius: 22px;\r\n        $top: 10px;\r\n\r\n        &::before,\r\n        &::after {\r\n                content: \"\";\r\n                width: 100%;\r\n                height: 100%;\r\n                position: absolute;\r\n                left: 0;\r\n                border: 1px solid #4E4E4E;\r\n                border-radius: $radius;\r\n                border-bottom: none;\r\n                box-sizing: border-box;\r\n        }\r\n\r\n        &::before {\r\n                top: 0;\r\n                z-index: 1;\r\n        }\r\n\r\n        &::after {\r\n                top: $top;\r\n                z-index: 2;\r\n        }\r\n\r\n        .line1,\r\n        .line2 {\r\n                width: 1px;\r\n                height: calc(100% - ($top*2) - ($radius*2));\r\n                position: absolute;\r\n                top: calc(($top*2) + $radius);\r\n                z-index: 4;\r\n                background: linear-gradient(180deg, rgba(32, 32, 32, 0), rgba(32, 32, 32, 0.5));\r\n        }\r\n\r\n        .line1 {\r\n                left: 0;\r\n        }\r\n\r\n        .line2 {\r\n                right: 0;\r\n        }\r\n\r\n        .line3,\r\n        .line4 {\r\n                width: $radius;\r\n                height: calc($radius + ($top*2));\r\n                position: absolute;\r\n                bottom: -($top*2);\r\n                z-index: 4;\r\n        }\r\n\r\n        .line3 {\r\n                left: 0;\r\n                background: linear-gradient(135deg, rgba(32, 32, 32, 0.5), rgba(32, 32, 32, 1) 80%);\r\n        }\r\n\r\n        .line4 {\r\n                right: 0;\r\n                background: linear-gradient(215deg, rgba(32, 32, 32, 0.5), rgba(32, 32, 32, 1) 80%);\r\n        }\r\n\r\n        .inner {\r\n                width: 100%;\r\n                height: 100%;\r\n                position: relative;\r\n                top: $top*2;\r\n                border: 1px solid #FFFFFF;\r\n                border-radius: $radius;\r\n                border-bottom: none;\r\n                z-index: 3;\r\n                box-sizing: border-box;\r\n        }\r\n}\r\n\r\n@media screen and (max-width: 1024px) {\r\n        .border3Box {\r\n                $radius: 5.3333vw;\r\n                $top: 2.6667vw;\r\n\r\n                &::before,\r\n                &::after {\r\n                        border-radius: $radius;\r\n                }\r\n\r\n                &::after {\r\n                        top: $top;\r\n                }\r\n\r\n                .line1,\r\n                .line2 {\r\n                        height: calc(100% - ($top*2) - ($radius*2));\r\n                        top: calc(($top*2) + $radius);\r\n                }\r\n\r\n                .line3,\r\n                .line4 {\r\n                        width: $radius;\r\n                        height: calc($radius + ($top*2));\r\n                        bottom: -($top*2);\r\n                }\r\n\r\n                .inner {\r\n                        top: $top*2;\r\n                        border-radius: $radius;\r\n                }\r\n        }\r\n}\r\n</style>"],"version":3}